qt_pydantic/__init__.py
qt_pydantic/annotations.py
qt_pydantic/wrapper.py
qt_pydantic-0.1.1.dist-info/licenses/LICENSE
qt_pydantic-0.1.1.dist-info/METADATA
qt_pydantic-0.1.1.dist-info/WHEEL
qt_pydantic-0.1.1.dist-info/top_level.txt
qt_pydantic-0.1.1.dist-info/RECORD
