Metadata-Version: 2.4
Name: qt-pydantic
Version: 0.1.1
Summary: Pydantic BaseModel Annotations for Qt
Author: Beat Reichenbach
License: MIT
Requires-Python: >=3.9
License-File: LICENSE
Requires-Dist: qtpy<3,>=2.0
Requires-Dist: pydantic<3,>=2.0
Provides-Extra: dev
Requires-Dist: black>=24.0; extra == "dev"
Requires-Dist: python-semantic-release>=9.0; extra == "dev"
Requires-Dist: PySide6; extra == "dev"
Requires-Dist: pytest>=8.0; extra == "dev"
Provides-Extra: pyside2
Requires-Dist: PySide2; extra == "pyside2"
Provides-Extra: pyside6
Requires-Dist: PySide6; extra == "pyside6"
Dynamic: license-file
